UC.vhd
library IEEE;
use IEEE.std_logic_1164.all;
use IEEE.numeric_std.all;

entity UC is
    port(
        clk,rst: in STD_LOGIC;
        instruction: in unsigned(15 downto 0);
        data_in_pc: out unsigned(7 downto 0);
        data_out_pc: in unsigned(7 downto 0);
        pc_att: out STD_LOGIC;
        rom_read: out STD_LOGIC;
        estado: in unsigned(1 downto 0);        
        reg_wr: out STD_LOGIC;
        ULA_op: out unsigned(1 downto 0);
        ULAsrcB: out STD_LOGIC;
        sel_regA, sel_regB, sel_reg_wr: out unsigned(2 downto 0)
    );
end entity UC;


architecture a_UC of UC is
    signal opcode: unsigned(5 downto 0);
    signal jump_en: STD_LOGIC;
begin
    pc_att <= '1' when estado = "00" else '0';
    rom_read <= '1' when estado = "01" else '0';
    
    opcode <= instruction(15 downto 10);
    
    jump_en <= '1' when opcode="011111" else '0'; --jump
    
    data_in_pc <= instruction(7 downto 0) when jump_en = '1' else data_out_pc+1;
    
    ULA_op <= "00" when opcode(1 downto 0) ="00" else -- soma
              "01" when opcode(1 downto 0) ="01" else -- sub
              "10" when opcode(1 downto 0) ="10" else -- and
              "11"; -- maior que
    
    sel_regA <= "000" when opcode(4 downto 3) = "11" else
                 instruction(9 downto 7);
    
    sel_regB <= instruction(6 downto 4);
    
    sel_reg_wr <= instruction(9 downto 7);
    
    ULAsrcB <= opcode(2);
    
    reg_wr <= opcode(5) when estado ="10" else '0';
    
end architecture a_UC;

mux2x1.vhd
library IEEE;
use IEEE.std_logic_1164.all;
use IEEE.numeric_std.all;

entity mux2x1 is
    port(
        sel               : in STD_LOGIC;
        data_I0, data_I1  : in unsigned (15 downto 0);
        data_O0           : out unsigned (15 downto 0)
    );
end entity mux2x1;

architecture a_mux2x1 of mux2x1 is
begin
    data_O0 <=    data_I0 when sel='0' else
                  data_I1 when sel='1' else
                  "0000000000000000";
end architecture a_mux2x1;

ULA.vhd
-- Pedro Augusto Tortola Pereira
-- Pedro Henrique Fracaro Kiche

library IEEE;
use IEEE.std_logic_1164.all;
use IEEE.numeric_std.all;

-- operação  sel_op
--   A+B       00
--   A-B       01
--   A&B       10
--   A>B       11


entity ULA is
    port(
        ula_in_A: in unsigned(15 downto 0);
        ula_in_B: in unsigned(15 downto 0);
        
        ula_out: out unsigned(15 downto 0);
        ula_greater_flag: out STD_LOGIC;
        
        sel_op: in unsigned(1 downto 0)
    );
end entity ULA;
architecture a_ULA of ULA is
begin
    ula_out <=  ula_in_A + ula_in_B when sel_op = "00" else
                ula_in_A - ula_in_B when sel_op = "01" else
                ula_in_A and ula_in_B when sel_op = "10" else
                "0000000000000000";
    
    ula_greater_flag <= '1' when sel_op = "11" and ula_in_A > ula_in_B and ula_in_A(15) = '0' and ula_in_B(15) = '0' else
                '1' when sel_op = "11" and ula_in_A > ula_in_B and ula_in_A(15) = '1' and ula_in_B(15) = '1' else
                '1' when sel_op = "11" and ula_in_A(15) = '0' and ula_in_B(15) = '1' else
                '0';
    
end architecture a_ULA;

reg16bits.vhd
library IEEE;
use IEEE.std_logic_1164.all;
use IEEE.numeric_std.all; 

entity reg16bits is
    port(
        clk: in STD_LOGIC;
        rst: in STD_LOGIC;
        wr_en: in STD_LOGIC;
        data_in: in unsigned(15 downto 0);
        data_out: out unsigned(15 downto 0)
    );
end entity reg16bits;

architecture a_reg16bits of reg16bits is
    
    signal data_register : unsigned(15 downto 0);

begin
    process(clk,rst,wr_en)
    begin
        if rst = '1' then
            data_register <= "0000000000000000";
        elsif wr_en = '1' then
            if rising_edge(clk) then 
                data_register <= data_in;
            end if;
        end if;
    end process;
    
    data_out <= data_register;
    
end architecture a_reg16bits;

BancoRegistradores.vhd
library IEEE;
use IEEE.std_logic_1164.all;
use IEEE.numeric_std.all;

entity BancoRegistradores is
    port(
        clk: in STD_LOGIC;
        rst: in STD_LOGIC;
        wr_en: in STD_LOGIC;
        
        sel_reg_write: in unsigned(2 downto 0);
        sel_regA_read: in unsigned(2 downto 0);
        sel_regB_read: in unsigned(2 downto 0);
        
        data_in_banco: in unsigned(15 downto 0);
        data_out_regA: out unsigned(15 downto 0);
        data_out_regB: out unsigned(15 downto 0)
        
    );
end entity BancoRegistradores;

architecture a_BancoRegistradores of BancoRegistradores is
    component reg16bits is
        port
        (
            clk      : IN STD_LOGIC ;
            rst      : IN STD_LOGIC ;
            wr_en    : IN STD_LOGIC ;
            data_in  : IN unsigned (15 downto 0);
            data_out : OUT unsigned (15 downto 0)
        );
    end component;
    constant reg0_wr_en : STD_LOGIC := '0';
    signal reg0_out, reg1_out, reg2_out, reg3_out, reg4_out, reg5_out, reg6_out, reg7_out: unsigned(15 downto 0);
    signal  reg1_wr_en, reg2_wr_en, reg3_wr_en, reg4_wr_en, reg5_wr_en, reg6_wr_en, reg7_wr_en: STD_LOGIC;

begin
    reg0: reg16bits port map(clk=>clk, rst=>rst, wr_en => reg0_wr_en, data_in=>data_in_banco, data_out=>reg0_out);
    reg1: reg16bits port map(clk=>clk, rst=>rst, wr_en => reg1_wr_en, data_in=>data_in_banco, data_out=>reg1_out);
    reg2: reg16bits port map(clk=>clk, rst=>rst, wr_en => reg2_wr_en, data_in=>data_in_banco, data_out=>reg2_out);
    reg3: reg16bits port map(clk=>clk, rst=>rst, wr_en => reg3_wr_en, data_in=>data_in_banco, data_out=>reg3_out);
    reg4: reg16bits port map(clk=>clk, rst=>rst, wr_en => reg4_wr_en, data_in=>data_in_banco, data_out=>reg4_out);
    reg5: reg16bits port map(clk=>clk, rst=>rst, wr_en => reg5_wr_en, data_in=>data_in_banco, data_out=>reg5_out);
    reg6: reg16bits port map(clk=>clk, rst=>rst, wr_en => reg6_wr_en, data_in=>data_in_banco, data_out=>reg6_out);
    reg7: reg16bits port map(clk=>clk, rst=>rst, wr_en => reg7_wr_en, data_in=>data_in_banco, data_out=>reg7_out);
    
    reg1_wr_en <='1' when sel_reg_write = "001" and wr_en = '1' else '0';
    reg2_wr_en <='1' when sel_reg_write = "010" and wr_en = '1' else '0';
    reg3_wr_en <='1' when sel_reg_write = "011" and wr_en = '1' else '0';
    reg4_wr_en <='1' when sel_reg_write = "100" and wr_en = '1' else '0';
    reg5_wr_en <='1' when sel_reg_write = "101" and wr_en = '1' else '0';
    reg6_wr_en <='1' when sel_reg_write = "110" and wr_en = '1' else '0';
    reg7_wr_en <='1' when sel_reg_write = "111" and wr_en = '1' else '0';
    
    data_out_regA <=    reg0_out when sel_regA_read ="000" else
                        reg1_out when sel_regA_read ="001" else
                        reg2_out when sel_regA_read ="010" else
                        reg3_out when sel_regA_read ="011" else
                        reg4_out when sel_regA_read ="100" else
                        reg5_out when sel_regA_read ="101" else
                        reg6_out when sel_regA_read ="110" else
                        reg7_out when sel_regA_read ="111" else
                        "0000000000000000";

    data_out_regB <=    reg0_out when sel_regB_read ="000" else
                        reg1_out when sel_regB_read ="001" else
                        reg2_out when sel_regB_read ="010" else
                        reg3_out when sel_regB_read ="011" else
                        reg4_out when sel_regB_read ="100" else
                        reg5_out when sel_regB_read ="101" else
                        reg6_out when sel_regB_read ="110" else
                        reg7_out when sel_regB_read ="111" else
                        "0000000000000000";

end architecture a_BancoRegistradores;

ROM.vhd
library IEEE;
use IEEE.std_logic_1164.all;
use IEEE.numeric_std.all;

entity ROM is
    port(
        clk : in STD_LOGIC;
        adress: in unsigned(7 downto 0);
        data_ROM: out unsigned(15 downto 0);
        rom_read: in STD_LOGIC
    );
end entity ROM;

architecture a_ROM of ROM is
    type mem is array (0 to 127) of unsigned(15 downto 0);
    constant rom_content : mem := (
        0=> B"0000000000000000",
        1=> B"111100_011_0000101",
        2=> B"111100_100_0001000",
        3=> B"100001_101_101_0000",
        4=> B"100000_011_100_0000",
        5=> B"1_01_0_00_101_011_0000",
        6=> B"100101_101_0000001",
        7=> B"011111_00_00010100",
        8=> B"100101_101_0000001",
        9=> B"100101_101_0000001",
        10=> B"100101_101_0000001",
        11=> B"100101_101_0000001",
        12=> B"100101_101_0000001",
        13=> B"100101_101_0000001",
        14=> B"100101_101_0000001",
        15=> B"100101_101_0000001",
        16=> B"100101_101_0000001",
        17=> B"100101_101_0000001",
        18=> B"100101_101_0000001",
        19=> B"100101_101_0000001",
        20=> B"100001_011_011_0000",
        21=> B"100000_011_101_0000",
        22=> B"011111_00_00000011",
        others => (others => '0')
    );
begin
    process(clk)
    begin
        if(rom_read = '1') then
            if rising_edge(clk) then
                data_ROM <= rom_content(to_integer(adress));
            end if;
        end if;
    end process;

end architecture a_ROM;

PC.vhd
library ieee;
use ieee.std_logic_1164.all;
use ieee.numeric_std.all;

entity PC is
    port
    (
        clk_pc             : in std_logic;
        wr_en              : in std_logic;
        rst                : in std_logic;
        data_in_pc         : in unsigned(7 downto 0);
        data_out_pc        : out unsigned(7 downto 0)
    );
end entity;

architecture a_PC of PC is
    signal registro : unsigned(7 downto 0);

begin
    process(rst,clk_pc,wr_en) 
    begin
        if rst = '1' then
            registro <= "00000000";
        elsif wr_en = '1' then 
            if rising_edge(clk_pc) then
                registro <= data_in_pc;
            end if;
        end if;
    end process;

    data_out_pc <= registro; 

end architecture;

MaquinaEstados.vhd
library IEEE;
use IEEE.std_logic_1164.all;
use IEEE.numeric_std.all;  

entity MaquinaEstados is
    port(
        clk: in STD_LOGIC;
        rst: in STD_LOGIC;
        estado: out unsigned(1 downto 0)
    );
end entity MaquinaEstados;

architecture a_MaquinaEstados of MaquinaEstados is
    signal estado_s: unsigned(1 downto 0);
begin
    process(clk,rst)
    begin
        if(rst = '1') then
            estado_s <= "00";
        elsif (rising_edge(clk)) then 
            if estado_s = "01" then 
                estado_s <= "00";
             else
                estado_s <= estado_s + 1;
            end if;
        end if;
    end process;
    estado <= estado_s;

end architecture a_MaquinaEstados;

Processador.vhd
library IEEE;
use IEEE.std_logic_1164.all;
use IEEE.numeric_std.all;

entity Processador is
    port(
        clk: in STD_LOGIC;
        rst: in STD_LOGIC;
        
        tl_estado: out unsigned(1 downto 0);
        tl_PC: out unsigned(7 downto 0);
        tl_instrucao: out unsigned(15 downto 0);
        tl_Reg1_out: out unsigned(15 downto 0);
        tl_Reg2_out: out unsigned(15 downto 0);
        tl_ULA_out:  out unsigned(15 downto 0)
    );
end entity Processador;

architecture a_Processador of Processador is
    component MaquinaEstados is
        port
        (
            clk    : IN STD_LOGIC ;
            rst    : IN STD_LOGIC ;
            estado : OUT unsigned (1 downto 0)
        );
    end component;
    
    component PC is
        port
        (
            clk_pc      : IN std_logic ;
            wr_en       : IN std_logic ;
            rst         : IN std_logic ;
            data_in_pc  : IN unsigned (7 downto 0);
            data_out_pc : OUT unsigned (7 downto 0)
        );
    end component;
    
    component ROM is
        port
        (
            clk      : IN STD_LOGIC ;
            adress   : IN unsigned (7 downto 0);
            data_ROM : OUT unsigned (15 downto 0);
            rom_read : IN STD_LOGIC
        );
    end component;
    
    component BancoRegistradores is
        port
        (
            clk           : IN STD_LOGIC ;
            rst           : IN STD_LOGIC ;
            wr_en         : IN STD_LOGIC ;
            sel_reg_write : IN unsigned (2 downto 0);
            sel_regA_read : IN unsigned (2 downto 0);
            sel_regB_read : IN unsigned (2 downto 0);
            data_in_banco : IN unsigned (15 downto 0);
            data_out_regA : OUT unsigned (15 downto 0);
            data_out_regB : OUT unsigned (15 downto 0)
        );
    end component;
    
    component ULA is
        port
        (
            ula_in_A         : IN unsigned (15 downto 0);
            ula_in_B         : IN unsigned (15 downto 0);
            ula_out          : OUT unsigned (15 downto 0);
            ula_greater_flag : OUT STD_LOGIC ;
            sel_op           : IN unsigned (1 downto 0)
        );
    end component;
    
    component mux2x1 is
        port
        (
            sel     : IN STD_LOGIC ;
            data_I0 : IN unsigned (15 downto 0);
            data_I1 : IN unsigned (15 downto 0);
            data_O0 : OUT unsigned (15 downto 0)
        );
    end component;
    
    component UC is
        port
        (
            clk         : IN STD_LOGIC ;
            rst         : IN STD_LOGIC ;
            instruction : IN unsigned (15 downto 0);
            data_in_pc  : OUT unsigned (7 downto 0);
            data_out_pc : IN unsigned (7 downto 0);
            pc_att      : OUT STD_LOGIC ;
            rom_read    : OUT STD_LOGIC ;
            estado      : IN unsigned (1 downto 0);
            reg_wr      : OUT STD_LOGIC ;
            ULA_op      : OUT unsigned (1 downto 0);
            ULAsrcB     : OUT STD_LOGIC ;
            sel_regA    : OUT unsigned (2 downto 0);
            sel_regB    : OUT unsigned (2 downto 0);
            sel_reg_wr  : OUT unsigned (2 downto 0)
        );
    end component;
    
    signal estado_s, ULA_op_s: unsigned(1 downto 0);
    signal pc_en_s,rom_read_s, reg_wr_en_s: STD_LOGIC;
    signal data_in_pc_s, data_out_pc_s: unsigned(7 downto 0);
    signal sel_reg_wr_s, sel_regA_s, sel_regB_s: unsigned(2 downto 0);
    signal regA_out_s, regB_out_s, ULA_out_s, instruction_s:unsigned(15 downto 0);
    signal mux_1_out_s: unsigned(15 downto 0);
    signal ULA_out_logic_s: STD_LOGIC;
    signal ULAsrcB_s: STD_LOGIC;
    signal const: unsigned(15 downto 0);
    
begin
    maqEstado0: MaquinaEstados
    port map
    (
        clk    => clk,
        rst    => rst,
        estado => estado_s
    );
    
    pc0: PC
    port map
    (
        clk_pc      => clk,
        wr_en       => pc_en_s,
        rst         => rst,
        data_in_pc  => data_in_pc_s,
        data_out_pc => data_out_pc_s
    );
    
    rom0: ROM
    port map
    (
        clk      => clk,
        adress   => data_out_pc_s,
        data_ROM => instruction_s,
        rom_read => rom_read_s
    );
    
    bancoReg0: BancoRegistradores
    port map
    (
        clk           => clk,
        rst           => rst,
        wr_en         => reg_wr_en_s,
        sel_reg_write => sel_reg_wr_s,
        sel_regA_read => sel_regA_s,
        sel_regB_read => sel_regB_s,
        data_in_banco => ULA_out_s,
        data_out_regA => regA_out_s,
        data_out_regB => regB_out_s
    );
    
    ula0: ULA
    port map
    (
        ula_in_A         => regA_out_s,
        ula_in_B         => mux_1_out_s,
        ula_out          => ULA_out_s,
        ula_greater_flag => ULA_out_logic_s,
        sel_op           => ULA_op_s
    );
    
    mux2x1_1: mux2x1
    port map
    (
        sel     => ULAsrcB_s,
        data_I0 => regB_out_s,
        data_I1 => const,
        data_O0 => mux_1_out_s
    );
    
    uc0: UC
    port map
    (
        clk         => clk,
        rst         => rst,
        instruction => instruction_s,
        data_in_pc  => data_in_pc_s,
        data_out_pc => data_out_pc_s,
        pc_att      => pc_en_s,
        rom_read    => rom_read_s,
        estado      => estado_s,
        reg_wr      => reg_wr_en_s,
        ULA_op      => ULA_op_s,
        ULAsrcB     => ULAsrcB_s,
        sel_regA    => sel_regA_s,
        sel_regB    => sel_regB_s,
        sel_reg_wr  => sel_reg_wr_s
    );
    
    const <= ("000000000") & instruction_s(6 downto 0) when instruction_s(6) = '0' else
             ("111111111") & instruction_s(6 downto 0);
    
    tl_estado <= estado_s;
    tl_PC <= data_out_pc_s;
    tl_instrucao <= instruction_s;
    tl_Reg1_out <= regA_out_s;
    tl_Reg2_out <= regB_out_s;
    tl_ULA_out <= ULA_out_s;

end architecture a_Processador;

Processador_tb.vhd
library IEEE;
use IEEE.std_logic_1164.all;
use IEEE.numeric_std.all;

entity Processador_tb is
end entity Processador_tb;

architecture a_Processador_tb of Processador_tb is
    component Processador is
        port
        (
            clk          : IN STD_LOGIC ;
            rst          : IN STD_LOGIC ;
            tl_estado    : OUT unsigned (1 downto 0);
            tl_PC        : OUT unsigned (7 downto 0);
            tl_instrucao : OUT unsigned (15 downto 0);
            tl_Reg1_out  : OUT unsigned (15 downto 0);
            tl_Reg2_out  : OUT unsigned (15 downto 0);
            tl_ULA_out   : OUT unsigned (15 downto 0)
        );
    end component;
    constant period_time: time := 100 ns;
    signal finished: STD_LOGIC := '0';
    signal clk, rst: STD_LOGIC;
    
    signal tl_estado    :  unsigned (1 downto 0);
    signal tl_PC        :  unsigned (7 downto 0);
    signal tl_instrucao :  unsigned (15 downto 0);
    signal tl_Reg1_out  :  unsigned (15 downto 0);
    signal tl_Reg2_out  :  unsigned (15 downto 0);
    signal tl_ULA_out   :  unsigned (15 downto 0);
    
begin
    
    doubleP: Processador
    port map
    (
        clk          => clk,
        rst          => rst,
        tl_estado    => tl_estado,
        tl_PC        => tl_PC,
        tl_instrucao => tl_instrucao,
        tl_Reg1_out  => tl_Reg1_out,
        tl_Reg2_out  => tl_Reg2_out,
        tl_ULA_out   => tl_ULA_out
    );
    
    reset_global:process
    begin
        rst <= '1';
        wait for period_time*2;
        rst <= '0';
        wait;
    end process;
    
    sim_time_proc:process
    begin 
        wait for 10 us;
        finished <= '1';
        wait;
    end process sim_time_proc;
    
    clk_proc:process
    begin
        while finished /= '1' loop
            clk<='0';
            wait for period_time/2;
            clk <= '1';
            wait for period_time/2;
        end loop;
        wait;
    end process clk_proc;
    
end architecture a_Processador_tb;

Processador_tb.vcd
$date
  Sun May 22 15:29:32 2022
$end
$version
  GHDL v0
$end
$timescale
  1 fs
$end
$scope module standard $end
$upscope $end
$scope module std_logic_1164 $end
$upscope $end
$scope module numeric_std $end
$upscope $end
$scope module processador_tb $end
$var reg 1 ! finished $end
$var reg 1 " clk $end
$var reg 1 # rst $end
$var reg 2 $ tl_estado[1:0] $end
$var reg 8 % tl_pc[7:0] $end
$var reg 16 & tl_instrucao[15:0] $end
$var reg 16 ' tl_reg1_out[15:0] $end
$var reg 16 ( tl_reg2_out[15:0] $end
$var reg 16 ) tl_ula_out[15:0] $end
$scope module doublep $end
$var reg 1 * clk $end
$var reg 1 + rst $end
$var reg 2 , tl_estado[1:0] $end
$var reg 8 - tl_pc[7:0] $end
$var reg 16 . tl_instrucao[15:0] $end
$var reg 16 / tl_reg1_out[15:0] $end
$var reg 16 0 tl_reg2_out[15:0] $end
$var reg 16 1 tl_ula_out[15:0] $end
$var reg 2 2 estado_s[1:0] $end
$var reg 2 3 ula_op_s[1:0] $end
$var reg 1 4 pc_en_s $end
$var reg 1 5 rom_read_s $end
$var reg 1 6 reg_wr_en_s $end
$var reg 8 7 data_in_pc_s[7:0] $end
$var reg 8 8 data_out_pc_s[7:0] $end
$var reg 3 9 sel_reg_wr_s[2:0] $end
$var reg 3 : sel_rega_s[2:0] $end
$var reg 3 ; sel_regb_s[2:0] $end
$var reg 16 < rega_out_s[15:0] $end
$var reg 16 = regb_out_s[15:0] $end
$var reg 16 > ula_out_s[15:0] $end
$var reg 16 ? instruction_s[15:0] $end
$var reg 16 @ mux_1_out_s[15:0] $end
$var reg 1 A ula_out_logic_s $end
$var reg 1 B ulasrcb_s $end
$var reg 16 C const[15:0] $end
$scope module maqestado0 $end
$var reg 1 D clk $end
$var reg 1 E rst $end
$var reg 2 F estado[1:0] $end
$var reg 2 G estado_s[1:0] $end
$upscope $end
$scope module pc0 $end
$var reg 1 H clk_pc $end
$var reg 1 I wr_en $end
$var reg 1 J rst $end
$var reg 8 K data_in_pc[7:0] $end
$var reg 8 L data_out_pc[7:0] $end
$var reg 8 M registro[7:0] $end
$upscope $end
$scope module rom0 $end
$var reg 1 N clk $end
$var reg 8 O adress[7:0] $end
$var reg 16 P data_rom[15:0] $end
$var reg 1 Q rom_read $end
$upscope $end
$scope module bancoreg0 $end
$var reg 1 R clk $end
$var reg 1 S rst $end
$var reg 1 T wr_en $end
$var reg 3 U sel_reg_write[2:0] $end
$var reg 3 V sel_rega_read[2:0] $end
$var reg 3 W sel_regb_read[2:0] $end
$var reg 16 X data_in_banco[15:0] $end
$var reg 16 Y data_out_rega[15:0] $end
$var reg 16 Z data_out_regb[15:0] $end
$var reg 16 [ reg0_out[15:0] $end
$var reg 16 \ reg1_out[15:0] $end
$var reg 16 ] reg2_out[15:0] $end
$var reg 16 ^ reg3_out[15:0] $end
$var reg 16 _ reg4_out[15:0] $end
$var reg 16 ` reg5_out[15:0] $end
$var reg 16 a reg6_out[15:0] $end
$var reg 16 b reg7_out[15:0] $end
$var reg 1 c reg1_wr_en $end
$var reg 1 d reg2_wr_en $end
$var reg 1 e reg3_wr_en $end
$var reg 1 f reg4_wr_en $end
$var reg 1 g reg5_wr_en $end
$var reg 1 h reg6_wr_en $end
$var reg 1 i reg7_wr_en $end
$scope module reg0 $end
$var reg 1 j clk $end
$var reg 1 k rst $end
$var reg 1 l wr_en $end
$var reg 16 m data_in[15:0] $end
$var reg 16 n data_out[15:0] $end
$var reg 16 o data_register[15:0] $end
$upscope $end
$scope module reg1 $end
$var reg 1 p clk $end
$var reg 1 q rst $end
$var reg 1 r wr_en $end
$var reg 16 s data_in[15:0] $end
$var reg 16 t data_out[15:0] $end
$var reg 16 u data_register[15:0] $end
$upscope $end
$scope module reg2 $end
$var reg 1 v clk $end
$var reg 1 w rst $end
$var reg 1 x wr_en $end
$var reg 16 y data_in[15:0] $end
$var reg 16 z data_out[15:0] $end
$var reg 16 { data_register[15:0] $end
$upscope $end
$scope module reg3 $end
$var reg 1 | clk $end
$var reg 1 } rst $end
$var reg 1 !" wr_en $end
$var reg 16 "" data_in[15:0] $end
$var reg 16 #" data_out[15:0] $end
$var reg 16 $" data_register[15:0] $end
$upscope $end
$scope module reg4 $end
$var reg 1 %" clk $end
$var reg 1 &" rst $end
$var reg 1 '" wr_en $end
$var reg 16 (" data_in[15:0] $end
$var reg 16 )" data_out[15:0] $end
$var reg 16 *" data_register[15:0] $end
$upscope $end
$scope module reg5 $end
$var reg 1 +" clk $end
$var reg 1 ," rst $end
$var reg 1 -" wr_en $end
$var reg 16 ." data_in[15:0] $end
$var reg 16 /" data_out[15:0] $end
$var reg 16 0" data_register[15:0] $end
$upscope $end
$scope module reg6 $end
$var reg 1 1" clk $end
$var reg 1 2" rst $end
$var reg 1 3" wr_en $end
$var reg 16 4" data_in[15:0] $end
$var reg 16 5" data_out[15:0] $end
$var reg 16 6" data_register[15:0] $end
$upscope $end
$scope module reg7 $end
$var reg 1 7" clk $end
$var reg 1 8" rst $end
$var reg 1 9" wr_en $end
$var reg 16 :" data_in[15:0] $end
$var reg 16 ;" data_out[15:0] $end
$var reg 16 <" data_register[15:0] $end
$upscope $end
$upscope $end
$scope module ula0 $end
$var reg 16 =" ula_in_a[15:0] $end
$var reg 16 >" ula_in_b[15:0] $end
$var reg 16 ?" ula_out[15:0] $end
$var reg 1 @" ula_greater_flag $end
$var reg 2 A" sel_op[1:0] $end
$upscope $end
$scope module mux2x1_1 $end
$var reg 1 B" sel $end
$var reg 16 C" data_i0[15:0] $end
$var reg 16 D" data_i1[15:0] $end
$var reg 16 E" data_o0[15:0] $end
$upscope $end
$scope module uc0 $end
$var reg 1 F" clk $end
$var reg 1 G" rst $end
$var reg 16 H" instruction[15:0] $end
$var reg 8 I" data_in_pc[7:0] $end
$var reg 8 J" data_out_pc[7:0] $end
$var reg 1 K" pc_att $end
$var reg 1 L" rom_read $end
$var reg 2 M" estado[1:0] $end
$var reg 1 N" reg_wr $end
$var reg 2 O" ula_op[1:0] $end
$var reg 1 P" ulasrcb $end
$var reg 3 Q" sel_rega[2:0] $end
$var reg 3 R" sel_regb[2:0] $end
$var reg 3 S" sel_reg_wr[2:0] $end
$var reg 6 T" opcode[5:0] $end
$var reg 1 U" jump_en $end
$upscope $end
$upscope $end
$upscope $end
$enddefinitions $end
#0
0!
0"
1#
b00 $
b00000000 %
bUUUUUUUUUUUUUUUU &
b0000000000000000 '
b0000000000000000 (
b0000000000000000 )
0*
1+
b00 ,
b00000000 -
bUUUUUUUUUUUUUUUU .
b0000000000000000 /
b0000000000000000 0
b0000000000000000 1
b00 2
b11 3
14
05
06
b00000001 7
b00000000 8
bUUU 9
bUUU :
bUUU ;
b0000000000000000 <
b0000000000000000 =
b0000000000000000 >
bUUUUUUUUUUUUUUUU ?
b0000000000000000 @
0A
UB
b111111111UUUUUUU C
0D
1E
b00 F
b00 G
0H
1I
1J
b00000001 K
b00000000 L
b00000000 M
0N
b00000000 O
bUUUUUUUUUUUUUUUU P
0Q
0R
1S
0T
bUUU U
bUUU V
bUUU W
b0000000000000000 X
b0000000000000000 Y
b0000000000000000 Z
b0000000000000000 [
b0000000000000000 \
b0000000000000000 ]
b0000000000000000 ^
b0000000000000000 _
b0000000000000000 `
b0000000000000000 a
b0000000000000000 b
0c
0d
0e
0f
0g
0h
0i
0j
1k
0l
b0000000000000000 m
b0000000000000000 n
b0000000000000000 o
0p
1q
0r
b0000000000000000 s
b0000000000000000 t
b0000000000000000 u
0v
1w
0x
b0000000000000000 y
b0000000000000000 z
b0000000000000000 {
0|
1}
0!"
b0000000000000000 ""
b0000000000000000 #"
b0000000000000000 $"
0%"
1&"
0'"
b0000000000000000 ("
b0000000000000000 )"
b0000000000000000 *"
0+"
1,"
0-"
b0000000000000000 ."
b0000000000000000 /"
b0000000000000000 0"
01"
12"
03"
b0000000000000000 4"
b0000000000000000 5"
b0000000000000000 6"
07"
18"
09"
b0000000000000000 :"
b0000000000000000 ;"
b0000000000000000 <"
b0000000000000000 ="
b0000000000000000 >"
b0000000000000000 ?"
0@"
b11 A"
UB"
b0000000000000000 C"
b111111111UUUUUUU D"
b0000000000000000 E"
0F"
1G"
bUUUUUUUUUUUUUUUU H"
b00000001 I"
b00000000 J"
1K"
0L"
b00 M"
0N"
b11 O"
UP"
bUUU Q"
bUUU R"
bUUU S"
bUUUUUU T"
0U"
#50000000
1"
1*
1D
1H
1N
1R
1j
1p
1v
1|
1%"
1+"
11"
17"
1F"
#100000000
0"
0*
0D
0H
0N
0R
0j
0p
0v
0|
0%"
0+"
01"
07"
0F"
#150000000
1"
1*
1D
1H
1N
1R
1j
1p
1v
1|
1%"
1+"
11"
17"
1F"
#200000000
0"
0#
0*
0+
0D
0E
0H
0J
0N
0R
0S
0j
0k
0p
0q
0v
0w
0|
0}
0%"
0&"
0+"
0,"
01"
02"
07"
08"
0F"
0G"
#250000000
1"
b01 $
b00000001 %
1*
b01 ,
b00000001 -
b01 2
04
15
b00000010 7
b00000001 8
1D
b01 F
b01 G
1H
0I
b00000010 K
b00000001 L
b00000001 M
1N
b00000001 O
1Q
1R
1j
1p
1v
1|
1%"
1+"
11"
17"
1F"
b00000010 I"
b00000001 J"
0K"
1L"
b01 M"
#300000000
0"
0*
0D
0H
0N
0R
0j
0p
0v
0|
0%"
0+"
01"
07"
0F"
#350000000
1"
b10 $
b1111000110000101 &
b0000000000000101 )
1*
b10 ,
b1111000110000101 .
b0000000000000101 1
b10 2
b00 3
05
16
b011 9
b000 :
b000 ;
b0000000000000101 >
b1111000110000101 ?
b0000000000000101 @
1B
b0000000000000101 C
1D
b10 F
b10 G
1H
1N
b1111000110000101 P
0Q
1R
1T
b011 U
b000 V
b000 W
b0000000000000101 X
1e
1j
b0000000000000101 m
1p
b0000000000000101 s
1v
b0000000000000101 y
1|
1!"
b0000000000000101 ""
1%"
b0000000000000101 ("
1+"
b0000000000000101 ."
11"
b0000000000000101 4"
17"
b0000000000000101 :"
b0000000000000101 >"
b0000000000000101 ?"
b00 A"
1B"
b0000000000000101 D"
b0000000000000101 E"
1F"
b1111000110000101 H"
0L"
b10 M"
1N"
b00 O"
1P"
b000 Q"
b000 R"
b011 S"
b111100 T"
#400000000
0"
0*
0D
0H
0N
0R
0j
0p
0v
0|
0%"
0+"
01"
07"
0F"
#450000000
1"
b00 $
1*
b00 ,
b00 2
14
06
1D
b00 F
b00 G
1H
1I
1N
1R
0T
b0000000000000101 ^
0e
1j
1p
1v
1|
0!"
b0000000000000101 #"
b0000000000000101 $"
1%"
1+"
11"
17"
1F"
1K"
b00 M"
0N"
#500000000
0"
0*
0D
0H
0N
0R
0j
0p
0v
0|
0%"
0+"
01"
07"
0F"
#550000000
1"
b01 $
b00000010 %
1*
b01 ,
b00000010 -
b01 2
04
15
b00000011 7
b00000010 8
1D
b01 F
b01 G
1H
0I
b00000011 K
b00000010 L
b00000010 M
1N
b00000010 O
1Q
1R
1j
1p
1v
1|
1%"
1+"
11"
17"
1F"
b00000011 I"
b00000010 J"
0K"
1L"
b01 M"
#600000000
0"
0*
0D
0H
0N
0R
0j
0p
0v
0|
0%"
0+"
01"
07"
0F"
#650000000
1"
b10 $
b1111001000001000 &
b0000000000001000 )
1*
b10 ,
b1111001000001000 .
b0000000000001000 1
b10 2
05
16
b100 9
b0000000000001000 >
b1111001000001000 ?
b0000000000001000 @
b0000000000001000 C
1D
b10 F
b10 G
1H
1N
b1111001000001000 P
0Q
1R
1T
b100 U
b0000000000001000 X
1f
1j
b0000000000001000 m
1p
b0000000000001000 s
1v
b0000000000001000 y
1|
b0000000000001000 ""
1%"
1'"
b0000000000001000 ("
1+"
b0000000000001000 ."
11"
b0000000000001000 4"
17"
b0000000000001000 :"
b0000000000001000 >"
b0000000000001000 ?"
b0000000000001000 D"
b0000000000001000 E"
1F"
b1111001000001000 H"
0L"
b10 M"
1N"
b100 S"
#700000000
0"
0*
0D
0H
0N
0R
0j
0p
0v
0|
0%"
0+"
01"
07"
0F"
#750000000
1"
b00 $
1*
b00 ,
b00 2
14
06
1D
b00 F
b00 G
1H
1I
1N
1R
0T
b0000000000001000 _
0f
1j
1p
1v
1|
1%"
0'"
b0000000000001000 )"
b0000000000001000 *"
1+"
11"
17"
1F"
1K"
b00 M"
0N"
#800000000
0"
0*
0D
0H
0N
0R
0j
0p
0v
0|
0%"
0+"
01"
07"
0F"
#850000000
1"
b01 $
b00000011 %
1*
b01 ,
b00000011 -
b01 2
04
15
b00000100 7
b00000011 8
1D
b01 F
b01 G
1H
0I
b00000100 K
b00000011 L
b00000011 M
1N
b00000011 O
1Q
1R
1j
1p
1v
1|
1%"
1+"
11"
17"
1F"
b00000100 I"
b00000011 J"
0K"
1L"
b01 M"
#900000000
0"
0*
0D
0H
0N
0R
0j
0p
0v
0|
0%"
0+"
01"
07"
0F"
